physics_based_pedestrian_modeling-0.3.8.dist-info/METADATA
physics_based_pedestrian_modeling-0.3.8.dist-info/WHEEL
physics_based_pedestrian_modeling-0.3.8.dist-info/entry_points.txt
physics_based_pedestrian_modeling-0.3.8.dist-info/licenses/LICENSE
physped/.main.py.~undo-tree~
physped/__init__.py
physped/_version.py
physped/conf/__init__.py
physped/conf/config.yaml
physped/conf/params/asdz_pf12.yaml
physped/conf/params/asdz_pf34.yaml
physped/conf/params/curved_paths.yaml
physped/conf/params/curved_paths_synthetic.yaml
physped/conf/params/eindhoven_pf34.yaml
physped/conf/params/fit/default_fit_param.yaml
physped/conf/params/force_field_plot/default_force_field_plot_params.yaml
physped/conf/params/grid/default_grid.yaml
physped/conf/params/grid_plot/default_grid_plot.yaml
physped/conf/params/histogram_plot/default_histogram_plot_params.yaml
physped/conf/params/intersecting_paths.yaml
physped/conf/params/intersecting_paths_synthetic.yaml
physped/conf/params/learn_piece_of_potential_plot/default_learn_piece_of_potential_plot.yaml
physped/conf/params/model/default_model_params.yaml
physped/conf/params/narrow_corridor.yaml
physped/conf/params/selection/default_selection.yaml
physped/conf/params/simulation/default_simulation_params.yaml
physped/conf/params/tests.yaml
physped/conf/params/trajectory_plot/default_trajectory_plot_params.yaml
physped/conf/params/user_input.yaml
physped/conf/params/utrecht_pf5.yaml
physped/conf/params/wide_corridor.yaml
physped/conf/science.mplstyle
physped/conf/science_no_latex.mplstyle
physped/core/__init__.py
physped/core/digitizers.py
physped/core/distribution_approximator.py
physped/core/langevin_model.py
physped/core/lattice.py
physped/core/lattice_selection.py
physped/core/parametrize_potential.py
physped/core/pedestrian_initializer.py
physped/core/pedestrian_simulator.py
physped/core/piecewise_potential.py
physped/core/slow_dynamics.py
physped/io/__init__.py
physped/io/readers.py
physped/io/writers.py
physped/main.py
physped/preprocessing/__init__.py
physped/preprocessing/trajectories.py
physped/processing_pipelines.py
physped/scripts/learn_potential_from_data.py
physped/scripts/merge_potentials.py
physped/scripts/physics-based-pedestrian-modeling.code-workspace
physics_based_pedestrian_modeling-0.3.8.dist-info/RECORD
