Metadata-Version: 2.1
Name: physics-based-pedestrian-modeling
Version: 0.3.8
Summary: Python package to create physics-based pedestrian models from crowd measurements
Author-Email: Cas Pouw <c.a.s.pouw@tue.nl>
License: BSD-3-Clause
Project-URL: Manuscript Physical Review E, https://doi.org/10.1103/PhysRevE.110.064102
Project-URL: Dataset Zenodo, https://doi.org/10.5281/zenodo.13784588
Project-URL: repository, https://github.com/c-pouw/physics-based-pedestrian-modeling/
Project-URL: documentation, https://c-pouw.github.io/physics-based-pedestrian-modeling/
Requires-Python: >=3.11
Requires-Dist: pandas==2.2.2
Requires-Dist: numpy>2.0.0
Requires-Dist: scipy<2.0.0,>=1.13.0
Requires-Dist: tqdm<5.0.0,>=4.66.2
Requires-Dist: sdeint<1.0.0,>=0.3.0
Requires-Dist: matplotlib<4.0.0,>=3.8.4
Requires-Dist: hydra-core<2.0.0,>=1.3.2
Requires-Dist: hydra-colorlog<2.0.0,>=1.2.0
Requires-Dist: urllib3<3.0.0,>=2.2.2
Requires-Dist: requests<3.0.0,>=2.32.3
Requires-Dist: h11>=0.15
Requires-Dist: pyarrow>=20.0.0
